ezsession/__init__.py
ezsession-0.0.16.dist-info/METADATA
ezsession-0.0.16.dist-info/WHEEL
ezsession-0.0.16.dist-info/top_level.txt
ezsession-0.0.16.dist-info/RECORD
