Metadata-Version: 2.1
Name: ezsession
Version: 0.0.16
Summary: A small useful Python module to abstract away the common auth header methods used by different software vendors. The output is a requests session with the authentication headers built in.
Author: Josh XT
Author-email: josh@devxt.com
Requires-Dist: requests
